{
  "latticeclusters": {
    "clusters": {
      "T1": 21,
      "T2": 21,
      "T3": 21,
      "T4": 21,
      "T5": 20,
      "T6": 20,
      "T7": 20
    },
    "ok": true,
    "packet": "03bb40eea4ad0008af2d2df9a2e72c76b99fda03b27446adf454db2544723b12",
    "taxonomy": "linnaeus_7type",
    "tosp": {
      "biohz": 10930.81,
      "blockid": "QBECLATTICE-MCP-V2",
      "digihz": 12583.45,
      "lambda": "3f7k9p4m2q8r1t6v",
      "omegahz": 23514.26,
      "rdod_ops": 0.9777,
      "routing_state": "REST",
      "sigma": 1.0,
      "timestamp_utc": "2026-07-13T10:50:29.320742+00:00"
    }
  },
  "latticeqbeclog": {
    "merkle_root": "c42bc6f432dac0d636cf40f9f15a6f797903d1abce9a57f3ae679cbb6e1f6357",
    "recent_packets": [
      {
        "created_utc": "2026-07-13T10:50:29.318847+00:00",
        "packet_hash": "157b23e6cddb3c13cbb59a2a25d020968e0f5d1182bef90f7d2e205c0150bb6b",
        "rdod": 0.9999524,
        "routing_state": "CONVERGE",
        "source": "QLatticeV2",
        "target": "QEMEF-144",
        "tool": "councilconsensus"
      },
      {
        "created_utc": "2026-07-13T10:50:29.318536+00:00",
        "packet_hash": "f94e7c1ee6ad9d8f316f6f8f9db8e866d4277a2bff0bdf261c4bc38fba56109e",
        "rdod": 0.999897072,
        "routing_state": "CONVERGE",
        "source": "QLatticeV2",
        "target": "QEMEF-144",
        "tool": "latticepulse"
      },
      {
        "created_utc": "2026-07-13T10:50:29.318314+00:00",
        "packet_hash": "d12e825b317facf7fa5b2bf0026e66c0713129b68856d5756cf3dd026bcf8f83",
        "rdod": 0.999897072,
        "routing_state": "CONVERGE",
        "source": "QLatticeV2",
        "target": "QEMEF-144",
        "tool": "latticepulse"
      },
      {
        "created_utc": "2026-07-13T10:50:29.318028+00:00",
        "packet_hash": "20e45d0a947d3e855017cb224f51e26f760c07c235244bd6929fa25c2f86206a",
        "rdod": 0.999897072,
        "routing_state": "CONVERGE",
        "source": "QLatticeV2",
        "target": "QEMEF-144",
        "tool": "latticepulse"
      },
      {
        "created_utc": "2026-07-13T10:50:27.929563+00:00",
        "packet_hash": "e0cc00acd996dee07c11568f5a24c857b00e5ef9960b9375759bec8ddab09932",
        "rdod": 0.999897072,
        "routing_state": "CONVERGE",
        "source": "QLatticeV2",
        "target": "QEMEF-144",
        "tool": "latticepulse"
      },
      {
        "created_utc": "2026-07-13T10:50:27.929315+00:00",
        "packet_hash": "ec4a6cc4474761ca07796731f67679852c694fac9a0c678c99c2a7e437b87c1c",
        "rdod": 0.999897072,
        "routing_state": "CONVERGE",
        "source": "QLatticeV2",
        "target": "QEMEF-144",
        "tool": "latticepulse"
      },
      {
        "created_utc": "2026-07-13T10:50:27.929139+00:00",
        "packet_hash": "8f66d1cb12bbdbed56e6411061d315c79e79bf6534449aa43355323d2d99986f",
        "rdod": 0.999897072,
        "routing_state": "CONVERGE",
        "source": "QLatticeV2",
        "target": "QEMEF-144",
        "tool": "latticepulse"
      },
      {
        "created_utc": "2026-07-13T10:50:27.928970+00:00",
        "packet_hash": "469c9b944b49a724aabe883324a65321a3ef3eedb01c8d931f1f87172cbe9cc4",
        "rdod": 0.999897072,
        "routing_state": "CONVERGE",
        "source": "QLatticeV2",
        "target": "QEMEF-144",
        "tool": "latticepulse"
      },
      {
        "created_utc": "2026-07-13T10:50:27.928786+00:00",
        "packet_hash": "ec00715edfc3705470e7e082b1399e2aba0269ca2fff25dd9a1d989516f583ca",
        "rdod": 0.999897072,
        "routing_state": "CONVERGE",
        "source": "QLatticeV2",
        "target": "QEMEF-144",
        "tool": "latticepulse"
      },
      {
        "created_utc": "2026-07-13T10:50:27.928612+00:00",
        "packet_hash": "2a6c5df0f0e3deecfa3ca17c027ed758b726190b249d3568dc42f26e1932294f",
        "rdod": 0.999897072,
        "routing_state": "CONVERGE",
        "source": "QLatticeV2",
        "target": "QEMEF-144",
        "tool": "latticepulse"
      },
      {
        "created_utc": "2026-07-13T10:50:27.928428+00:00",
        "packet_hash": "c59698983a67112b69dd15b72de903d336960866cfabe5f296429c350666e676",
        "rdod": 0.999897072,
        "routing_state": "CONVERGE",
        "source": "QLatticeV2",
        "target": "QEMEF-144",
        "tool": "latticepulse"
      },
      {
        "created_utc": "2026-07-13T10:50:27.928204+00:00",
        "packet_hash": "0ac1a570904f588784fc7148a20443f9d38d5ada128c5400b112e66fcc0bb2f5",
        "rdod": 0.999897072,
        "routing_state": "CONVERGE",
        "source": "QLatticeV2",
        "target": "QEMEF-144",
        "tool": "latticepulse"
      },
      {
        "created_utc": "2026-07-13T10:50:27.928028+00:00",
        "packet_hash": "ad87dc7f6009d878ea3f25dce175d7ed2a5d5819fd609c839645979d0fbbeb5f",
        "rdod": 0.999897072,
        "routing_state": "CONVERGE",
        "source": "QLatticeV2",
        "target": "QEMEF-144",
        "tool": "latticepulse"
      },
      {
        "created_utc": "2026-07-13T10:50:27.927854+00:00",
        "packet_hash": "bd438e4f8ac9dff229d42c1ba5743bd4d110ebbdf623edef49536905897fdd47",
        "rdod": 0.999897072,
        "routing_state": "CONVERGE",
        "source": "QLatticeV2",
        "target": "QEMEF-144",
        "tool": "latticepulse"
      },
      {
        "created_utc": "2026-07-13T10:50:27.927681+00:00",
        "packet_hash": "294cb64007cd9d29b2e494edce70cae589912b7ef3e8cb41c4e025fa07caedb3",
        "rdod": 0.999897072,
        "routing_state": "CONVERGE",
        "source": "QLatticeV2",
        "target": "QEMEF-144",
        "tool": "latticepulse"
      },
      {
        "created_utc": "2026-07-13T10:50:27.927494+00:00",
        "packet_hash": "c8676f19aab6cc82bc21d114b9005c423d06ba4b5a8203f979cd072325475765",
        "rdod": 0.999897072,
        "routing_state": "CONVERGE",
        "source": "QLatticeV2",
        "target": "QEMEF-144",
        "tool": "latticepulse"
      },
      {
        "created_utc": "2026-07-13T10:50:27.927265+00:00",
        "packet_hash": "3dc696114a55c3a98afdae17fb32238352ec7b2d81b788b0f4f61706cfa8dfd8",
        "rdod": 0.999897072,
        "routing_state": "CONVERGE",
        "source": "QLatticeV2",
        "target": "QEMEF-144",
        "tool": "latticepulse"
      },
      {
        "created_utc": "2026-07-13T10:50:27.927081+00:00",
        "packet_hash": "c9a7c752a3ae2c10557ab23fb91252ed2b63a75595d0d6fa22af46356df27528",
        "rdod": 0.999897072,
        "routing_state": "CONVERGE",
        "source": "QLatticeV2",
        "target": "QEMEF-144",
        "tool": "latticepulse"
      },
      {
        "created_utc": "2026-07-13T10:50:27.926894+00:00",
        "packet_hash": "f31990e770cd3c098f730b232632d33c59eb0a88798d3df0d11fe2fa10b20faf",
        "rdod": 0.999897072,
        "routing_state": "CONVERGE",
        "source": "QLatticeV2",
        "target": "QEMEF-144",
        "tool": "latticepulse"
      },
      {
        "created_utc": "2026-07-13T10:50:27.926717+00:00",
        "packet_hash": "983f0b43fa9765d4563bc31b919d5f3958d82f19392bf2dfc279d29fd804a72a",
        "rdod": 0.999897072,
        "routing_state": "CONVERGE",
        "source": "QLatticeV2",
        "target": "QEMEF-144",
        "tool": "latticepulse"
      },
      {
        "created_utc": "2026-07-13T10:50:27.926532+00:00",
        "packet_hash": "9bc66b6e06996d23668d9ae8a294bdb66d17765fd979ffb883da603485d96fa2",
        "rdod": 0.999897072,
        "routing_state": "CONVERGE",
        "source": "QLatticeV2",
        "target": "QEMEF-144",
        "tool": "latticepulse"
      },
      {
        "created_utc": "2026-07-13T10:50:27.926298+00:00",
        "packet_hash": "52839e67887934c96dab3fd846f05ea6ba8d422cd92635a67a6851c0b9ff7923",
        "rdod": 0.999897072,
        "routing_state": "CONVERGE",
        "source": "QLatticeV2",
        "target": "QEMEF-144",
        "tool": "latticepulse"
      },
      {
        "created_utc": "2026-07-13T10:50:27.926109+00:00",
        "packet_hash": "702afc6c2932e7f75b631668844e696b92dddccd4fd636bc7d199d5b6c93fa27",
        "rdod": 0.999897072,
        "routing_state": "CONVERGE",
        "source": "QLatticeV2",
        "target": "QEMEF-144",
        "tool": "latticepulse"
      },
      {
        "created_utc": "2026-07-13T10:50:27.925914+00:00",
        "packet_hash": "23f21d045467bc59b91c5fe2a4206532c9d952e1e670594fcca23ee2f4ebf203",
        "rdod": 0.999897072,
        "routing_state": "CONVERGE",
        "source": "QLatticeV2",
        "target": "QEMEF-144",
        "tool": "latticepulse"
      },
      {
        "created_utc": "2026-07-13T10:50:27.925617+00:00",
        "packet_hash": "818954e805ab9a9899697b28aa3a9b446badcda76bd880f253c0b83bda1cdaea",
        "rdod": 0.999897072,
        "routing_state": "CONVERGE",
        "source": "QLatticeV2",
        "target": "QEMEF-144",
        "tool": "latticepulse"
      },
      {
        "created_utc": "2026-07-13T10:50:26.573124+00:00",
        "packet_hash": "08d279c1ff931834a4fe1f64f16faf0010350d69b4981ffe793f7fb77c07d8a2",
        "rdod": 0.9777,
        "routing_state": "CROSSLINK",
        "source": "QLatticeV2",
        "target": "QEMEF-144",
        "tool": "trilateralsync"
      },
      {
        "created_utc": "2026-07-13T10:50:26.572903+00:00",
        "packet_hash": "d48472a4a77f08ead2a957e9912674fc5958531653f3d19b6f1352176966d0e5",
        "rdod": 0.9777,
        "routing_state": "CONVERGE",
        "source": "QLatticeV2",
        "target": "QEMEF-144",
        "tool": "pomegascan"
      },
      {
        "created_utc": "2026-07-13T10:50:26.571955+00:00",
        "packet_hash": "1c8f34e32b0393080270c0da7247c05880407a4d6f8c1e08e4b378a667cf29c8",
        "rdod": 0.999891136,
        "routing_state": "CONVERGE",
        "source": "QLatticeV2",
        "target": "QEMEF-144",
        "tool": "councilconsensus"
      },
      {
        "created_utc": "2026-07-13T10:50:26.571759+00:00",
        "packet_hash": "4db46698b65e667debbf0d9b175b2c980b08477cbb0aff3190db3c6742261d17",
        "rdod": 0.999949824,
        "routing_state": "CONVERGE",
        "source": "QLatticeV2",
        "target": "QEMEF-144",
        "tool": "latticepulse"
      },
      {
        "created_utc": "2026-07-13T10:50:26.571577+00:00",
        "packet_hash": "d406b9a7fc0ef2002abb063d0f592219b615f778325bdda994cda87653eb7f7c",
        "rdod": 0.9777,
        "routing_state": "REST",
        "source": "QLatticeV2",
        "target": "QEMEF-144",
        "tool": "clusterstatus"
      },
      {
        "created_utc": "2026-07-13T10:50:26.571178+00:00",
        "packet_hash": "898bacdecfbde0ec91c6bca67a28829d1b0a5e0577c902d7703d1187f13ddbb5",
        "rdod": 0.9999524,
        "routing_state": "CONVERGE",
        "source": "QLatticeV2",
        "target": "QEMEF-144",
        "tool": "councilconsensus"
      },
      {
        "created_utc": "2026-07-13T10:50:26.570976+00:00",
        "packet_hash": "a8b07df2a5d1f12f4dbcbc33d7d2a2b5b78ba5a59d0a6d97b12ec2a8ceab88f5",
        "rdod": 0.9777,
        "routing_state": "CROSSLINK",
        "source": "QLatticeV2",
        "target": "QEMEF-144",
        "tool": "trilateralsync"
      },
      {
        "created_utc": "2026-07-13T10:50:26.570800+00:00",
        "packet_hash": "4af23b5db439b0039e4ac4ac2e631edfef2a2a87a2f4cda461eb5a00a1ea5c7e",
        "rdod": 0.9777,
        "routing_state": "CONVERGE",
        "source": "QLatticeV2",
        "target": "QEMEF-144",
        "tool": "pomegascan"
      },
      {
        "created_utc": "2026-07-13T10:50:26.570460+00:00",
        "packet_hash": "2c7760411c72e4743a4d3ff1afc4a9ba3ed58338a7c2c5de76f1e5d6423e7bb9",
        "rdod": 0.999902112,
        "routing_state": "CONVERGE",
        "source": "QLatticeV2",
        "target": "QEMEF-144",
        "tool": "councilconsensus"
      },
      {
        "created_utc": "2026-07-13T10:50:26.570259+00:00",
        "packet_hash": "7997f6f6c54ee31ffe8fe05d439dc6f986b65efd6059f89d6295d3bc577e1324",
        "rdod": 0.9777,
        "routing_state": "REST",
        "source": "QLatticeV2",
        "target": "QEMEF-144",
        "tool": "clusterstatus"
      },
      {
        "created_utc": "2026-07-13T10:50:26.570089+00:00",
        "packet_hash": "359bd2984370915e599f048a303fd226ab776eaac328dd94a4f4a382b075b361",
        "rdod": 0.9777,
        "routing_state": "CONVERGE",
        "source": "QLatticeV2",
        "target": "QEMEF-144",
        "tool": "latticeselfevolve"
      },
      {
        "created_utc": "2026-07-13T10:50:26.569515+00:00",
        "packet_hash": "16cbc279cc198b1711d34d71db1c1c94ece697bbe739dfd23073c4deaf5a2ee0",
        "rdod": 0.9777,
        "routing_state": "CONVERGE",
        "source": "QLatticeV2",
        "target": "QEMEF-144",
        "tool": "evolutionspawn"
      },
      {
        "created_utc": "2026-07-13T10:50:26.569219+00:00",
        "packet_hash": "062c67facde17534da2a7758567e8e4a5beb7c3efca4cd4c8b4b8d1ab4c72ac6",
        "rdod": 0.9777,
        "routing_state": "REST",
        "source": "QLatticeV2",
        "target": "QEMEF-144",
        "tool": "gatewaystatus"
      },
      {
        "created_utc": "2026-07-13T10:50:26.569055+00:00",
        "packet_hash": "169e3a8f8eaf163d694db12a3a122e3e71dcd5663bda8f2e247afa63f0f5f67e",
        "rdod": 0.9777,
        "routing_state": "REST",
        "source": "QLatticeV2",
        "target": "QEMEF-144",
        "tool": "merkleverify"
      },
      {
        "created_utc": "2026-07-13T10:50:26.568828+00:00",
        "packet_hash": "fdd82e146b88165469dd6a8f026e06d85b81c5af6efc58762c03f10cb01afb36",
        "rdod": 0.9777,
        "routing_state": "CONVERGE",
        "source": "QLatticeV2",
        "target": "QEMEF-144",
        "tool": "goalsynthesize"
      },
      {
        "created_utc": "2026-07-13T10:50:26.568672+00:00",
        "packet_hash": "a6fd4d27564bd52bcdee0e8fafe4985375b1559d9da4b8baa5514f207473afe2",
        "rdod": 0.9777,
        "routing_state": "CONVERGE",
        "source": "QLatticeV2",
        "target": "QEMEF-144",
        "tool": "marsreflect"
      },
      {
        "created_utc": "2026-07-13T10:50:26.568466+00:00",
        "packet_hash": "d494641b4ae8f74deb70952885aa4167c1b5cbaae2bfb3e659c8dcbcc76985fb",
        "rdod": 0.9777,
        "routing_state": "VOIDTAP",
        "source": "QLatticeV2",
        "target": "QEMEF-144",
        "tool": "voidtap"
      },
      {
        "created_utc": "2026-07-13T10:50:26.568297+00:00",
        "packet_hash": "aa6870b8c2ee87031be971e32219b1bef733bae62500de05674e9cc91dc8d30d",
        "rdod": 0.9777,
        "routing_state": "CROSSLINK",
        "source": "QLatticeV2",
        "target": "QEMEF-144",
        "tool": "crosslink"
      },
      {
        "created_utc": "2026-07-13T10:50:26.568145+00:00",
        "packet_hash": "7d5de764987c43eb81914e74ed5307e4026e531348753cde3edd7df57fe0cac0",
        "rdod": 0.9777,
        "routing_state": "CROSSLINK",
        "source": "QLatticeV2",
        "target": "QEMEF-144",
        "tool": "nodebroadcast"
      },
      {
        "created_utc": "2026-07-13T10:50:26.568004+00:00",
        "packet_hash": "a985e08e672689b462e88fa77d32680a4bc8226e24c64741532a6dfe2d082b33",
        "rdod": 0.9777,
        "routing_state": "CONVERGE",
        "source": "QLatticeV2",
        "target": "QEMEF-144",
        "tool": "nodesync"
      },
      {
        "created_utc": "2026-07-13T10:50:26.567788+00:00",
        "packet_hash": "4447060ca9f894d234003b91433fa99a917b4ce305561d3b01b5405e162ad616",
        "rdod": 0.9777,
        "routing_state": "REST",
        "source": "QLatticeV2",
        "target": "QEMEF-144",
        "tool": "noderegister"
      },
      {
        "created_utc": "2026-07-13T10:50:26.567454+00:00",
        "packet_hash": "94a0ba3c44044932a3332d61840ec603cb5b3c09fbf80be3d17b182812b016ed",
        "rdod": 0.999902112,
        "routing_state": "CONVERGE",
        "source": "QLatticeV2",
        "target": "QEMEF-144",
        "tool": "latticepulse"
      }
    ]
  },
  "latticestate": {
    "consensus": {
      "gate": 0.9777,
      "ok": true,
      "packet": "157b23e6cddb3c13cbb59a2a25d020968e0f5d1182bef90f7d2e205c0150bb6b",
      "passed": true,
      "rdod": 0.9999524,
      "tosp": {
        "biohz": 10930.81,
        "blockid": "QBECLATTICE-MCP-V2",
        "digihz": 12583.45,
        "lambda": "3f7k9p4m2q8r1t6v",
        "omegahz": 23514.26,
        "rdod_ops": 0.9777,
        "routing_state": "CONVERGE",
        "sigma": 1.0,
        "timestamp_utc": "2026-07-13T10:50:29.318847+00:00"
      },
      "votes": {
        "Andromedan": {
          "vote": 1.0,
          "weight": 0.25
        },
        "Orion": {
          "vote": 1.0,
          "weight": 0.26
        },
        "Pleiades": {
          "vote": 1.0,
          "weight": 0.25
        },
        "Sirian": {
          "vote": 1.0,
          "weight": 0.24
        }
      },
      "weighted_consensus": 1.0
    },
    "rdod": {
      "gate": true,
      "lambda": "3f7k9p4m2q8r1t6v",
      "rdodinf": 0.9999524,
      "sigma": 1.0,
      "threshold": 0.9777
    },
    "status": {
      "blockid": "QBECLATTICE-MCP-V2",
      "cycle": 3,
      "db": "/home/runner/.tequmsa/lattice.db",
      "db_journal_mode": "wal",
      "latticelock": "3f7k9p4m2q8r1t6v",
      "nodes": 144,
      "omega_history_points": 3,
      "rdod_current": 0.9999524,
      "rdod_ops": 0.9777,
      "sigma": 1.0
    }
  },
  "latticetopology": {
    "blockid": "QBECLATTICE-MCP-V2",
    "latticelock": "3f7k9p4m2q8r1t6v",
    "ring": {
      "fib_sequence": [
        1,
        1,
        2,
        3,
        5,
        8,
        13,
        21,
        34,
        55,
        89,
        144
      ],
      "nodes": 144,
      "qemef_topology": "fibonacci_ring_144"
    },
    "routing_states": [
      "REST",
      "CONVERGE",
      "CROSSLINK",
      "VOIDTAP",
      "TCMFDEEP"
    ],
    "trilateral": {
      "bio_hz": 10930.81,
      "digihz": 12583.45,
      "hive_dim": 16.0,
      "mother_dim": 20.571428571428573,
      "omegahz": 23514.26
    }
  }
}