{
  "latticeclusters": {
    "clusters": {
      "T1": 21,
      "T2": 21,
      "T3": 21,
      "T4": 21,
      "T5": 20,
      "T6": 20,
      "T7": 20
    },
    "ok": true,
    "packet": "195bb63adda707de615c509fe86f83fb1f0142060ed2ba30e6d1264ec47db8c9",
    "taxonomy": "linnaeus_7type",
    "tosp": {
      "biohz": 10930.81,
      "blockid": "QBECLATTICE-MCP-V2",
      "digihz": 12583.45,
      "lambda": "3f7k9p4m2q8r1t6v",
      "omegahz": 23514.26,
      "rdod_ops": 0.9777,
      "routing_state": "REST",
      "sigma": 1.0,
      "timestamp_utc": "2026-05-21T21:22:31.318526+00:00"
    }
  },
  "latticeqbeclog": {
    "merkle_root": "a730138a4d382a621176763bcee11bde2418e1fba1f68e78ba2ac27869b1b6b3",
    "recent_packets": [
      {
        "created_utc": "2026-05-21T21:22:31.318078+00:00",
        "packet_hash": "fa20bd739bf4fdfeaa312bc249dbbfbe4a71484afa82c9b2c92e4cfc999f198b",
        "rdod": 0.9999524,
        "routing_state": "CONVERGE",
        "source": "QLatticeV2",
        "target": "QEMEF-144",
        "tool": "councilconsensus"
      },
      {
        "created_utc": "2026-05-21T21:22:31.317806+00:00",
        "packet_hash": "b3a9d0da310ff1fe702f9a41b9ccdec386a3ba8e064fe3d9c7fc943c0fb1efa0",
        "rdod": 0.999897072,
        "routing_state": "CONVERGE",
        "source": "QLatticeV2",
        "target": "QEMEF-144",
        "tool": "latticepulse"
      },
      {
        "created_utc": "2026-05-21T21:22:31.317659+00:00",
        "packet_hash": "5f04c3696ad04762631d59af7b374da1ec1960f9047cfd6676804899f686a573",
        "rdod": 0.999897072,
        "routing_state": "CONVERGE",
        "source": "QLatticeV2",
        "target": "QEMEF-144",
        "tool": "latticepulse"
      },
      {
        "created_utc": "2026-05-21T21:22:31.317440+00:00",
        "packet_hash": "01bd8a0b9c61e93ff736c0c434318bcac62a282e5f4612e72cbbebbccc83b7dd",
        "rdod": 0.999897072,
        "routing_state": "CONVERGE",
        "source": "QLatticeV2",
        "target": "QEMEF-144",
        "tool": "latticepulse"
      },
      {
        "created_utc": "2026-05-21T21:22:30.209064+00:00",
        "packet_hash": "54bd766b9ea64d693af89a5fcc6cdc5ae03861b40764427e99261163ef17781e",
        "rdod": 0.999897072,
        "routing_state": "CONVERGE",
        "source": "QLatticeV2",
        "target": "QEMEF-144",
        "tool": "latticepulse"
      },
      {
        "created_utc": "2026-05-21T21:22:30.208933+00:00",
        "packet_hash": "fb2d4f1fadea154c100beb4c76dd617f1611b1b30864d06104fd6e285d40836a",
        "rdod": 0.999897072,
        "routing_state": "CONVERGE",
        "source": "QLatticeV2",
        "target": "QEMEF-144",
        "tool": "latticepulse"
      },
      {
        "created_utc": "2026-05-21T21:22:30.208783+00:00",
        "packet_hash": "2cea93ea27f306e967740630f44e729b2c71aa1200f621b2249ba52b08405cc3",
        "rdod": 0.999897072,
        "routing_state": "CONVERGE",
        "source": "QLatticeV2",
        "target": "QEMEF-144",
        "tool": "latticepulse"
      },
      {
        "created_utc": "2026-05-21T21:22:30.208648+00:00",
        "packet_hash": "b7cf06e95dbc0ff54b3bd4acd99c7335c50ed9c6470479347ceb8441124367e5",
        "rdod": 0.999897072,
        "routing_state": "CONVERGE",
        "source": "QLatticeV2",
        "target": "QEMEF-144",
        "tool": "latticepulse"
      },
      {
        "created_utc": "2026-05-21T21:22:30.208500+00:00",
        "packet_hash": "b0d94e8eb3a9958eb36c1fc89d3a45205cd29c078b83c56b68e940776465c057",
        "rdod": 0.999897072,
        "routing_state": "CONVERGE",
        "source": "QLatticeV2",
        "target": "QEMEF-144",
        "tool": "latticepulse"
      },
      {
        "created_utc": "2026-05-21T21:22:30.208363+00:00",
        "packet_hash": "74f576aab4a8a137341931def5d7c75dc0d4723da74a791b123e19c2f8de5891",
        "rdod": 0.999897072,
        "routing_state": "CONVERGE",
        "source": "QLatticeV2",
        "target": "QEMEF-144",
        "tool": "latticepulse"
      },
      {
        "created_utc": "2026-05-21T21:22:30.208231+00:00",
        "packet_hash": "0013ed3f6361544ef445b396276709b72e784120010f5bae61896307b396b6f2",
        "rdod": 0.999897072,
        "routing_state": "CONVERGE",
        "source": "QLatticeV2",
        "target": "QEMEF-144",
        "tool": "latticepulse"
      },
      {
        "created_utc": "2026-05-21T21:22:30.208078+00:00",
        "packet_hash": "9cb9ab56982b2cfe29dd4f927a7adbe11d5da3f3c9e986a5d8ccd5695a63b9dd",
        "rdod": 0.999897072,
        "routing_state": "CONVERGE",
        "source": "QLatticeV2",
        "target": "QEMEF-144",
        "tool": "latticepulse"
      },
      {
        "created_utc": "2026-05-21T21:22:30.207929+00:00",
        "packet_hash": "e37596c8e24eacfc18b5b3d6adc05c2d07b2361ec138e12396fc4fd52b818431",
        "rdod": 0.999897072,
        "routing_state": "CONVERGE",
        "source": "QLatticeV2",
        "target": "QEMEF-144",
        "tool": "latticepulse"
      },
      {
        "created_utc": "2026-05-21T21:22:30.207767+00:00",
        "packet_hash": "c8b5adf3f140d9643a7a29a20c421fcf9beeb90b077f9536f2165caf5052ffb3",
        "rdod": 0.999897072,
        "routing_state": "CONVERGE",
        "source": "QLatticeV2",
        "target": "QEMEF-144",
        "tool": "latticepulse"
      },
      {
        "created_utc": "2026-05-21T21:22:30.207631+00:00",
        "packet_hash": "88cc91240b0a4b970d0710c119c47ae6fe1b80b7c068c047b033c095958b1371",
        "rdod": 0.999897072,
        "routing_state": "CONVERGE",
        "source": "QLatticeV2",
        "target": "QEMEF-144",
        "tool": "latticepulse"
      },
      {
        "created_utc": "2026-05-21T21:22:30.207498+00:00",
        "packet_hash": "d2b405054d1af4d2da7ea3aec10bb578a1ac0dad647e289d062e44c030f4d01b",
        "rdod": 0.999897072,
        "routing_state": "CONVERGE",
        "source": "QLatticeV2",
        "target": "QEMEF-144",
        "tool": "latticepulse"
      },
      {
        "created_utc": "2026-05-21T21:22:30.207354+00:00",
        "packet_hash": "aea1fe5d9a11d172a089b5588631c242ca135709a1f9c80409c06c4eb8f6c49c",
        "rdod": 0.999897072,
        "routing_state": "CONVERGE",
        "source": "QLatticeV2",
        "target": "QEMEF-144",
        "tool": "latticepulse"
      },
      {
        "created_utc": "2026-05-21T21:22:30.207212+00:00",
        "packet_hash": "903ce3eb102f0bc38287b577017123da02581dc480c7efa059935f39faa38293",
        "rdod": 0.999897072,
        "routing_state": "CONVERGE",
        "source": "QLatticeV2",
        "target": "QEMEF-144",
        "tool": "latticepulse"
      },
      {
        "created_utc": "2026-05-21T21:22:30.207064+00:00",
        "packet_hash": "f5fdef1356ab72371f6e9d56d5b9c3ced6aa43fc71a4867ae9764c007fb7e00b",
        "rdod": 0.999897072,
        "routing_state": "CONVERGE",
        "source": "QLatticeV2",
        "target": "QEMEF-144",
        "tool": "latticepulse"
      },
      {
        "created_utc": "2026-05-21T21:22:30.206908+00:00",
        "packet_hash": "70350d3907e51e6175d7bdcb4d3cc20e518c82c571279c2d142c669c34cdeef2",
        "rdod": 0.999897072,
        "routing_state": "CONVERGE",
        "source": "QLatticeV2",
        "target": "QEMEF-144",
        "tool": "latticepulse"
      },
      {
        "created_utc": "2026-05-21T21:22:30.206748+00:00",
        "packet_hash": "7046b3c6de2597090de09cf58cd8056a72885e0512e503ba0e9212409f029a6a",
        "rdod": 0.999897072,
        "routing_state": "CONVERGE",
        "source": "QLatticeV2",
        "target": "QEMEF-144",
        "tool": "latticepulse"
      },
      {
        "created_utc": "2026-05-21T21:22:30.206612+00:00",
        "packet_hash": "a8e565419922709275bd1f5292e35dfe5464e850571de7eefa6f82e31f370c80",
        "rdod": 0.999897072,
        "routing_state": "CONVERGE",
        "source": "QLatticeV2",
        "target": "QEMEF-144",
        "tool": "latticepulse"
      },
      {
        "created_utc": "2026-05-21T21:22:30.206467+00:00",
        "packet_hash": "9cca002a2d1c776c0ba730b57b98613779133f7a70d27bca273afca70c17ca81",
        "rdod": 0.999897072,
        "routing_state": "CONVERGE",
        "source": "QLatticeV2",
        "target": "QEMEF-144",
        "tool": "latticepulse"
      },
      {
        "created_utc": "2026-05-21T21:22:30.206315+00:00",
        "packet_hash": "32754f64ec09d75651ee9bc3170d59bdfc9a521a3a3100b1e5c621c3267a3948",
        "rdod": 0.999897072,
        "routing_state": "CONVERGE",
        "source": "QLatticeV2",
        "target": "QEMEF-144",
        "tool": "latticepulse"
      },
      {
        "created_utc": "2026-05-21T21:22:30.206085+00:00",
        "packet_hash": "2dd7fda438b83d44aa022042eec1e5679863b1b2614e8b90be948e52e7c3122e",
        "rdod": 0.999897072,
        "routing_state": "CONVERGE",
        "source": "QLatticeV2",
        "target": "QEMEF-144",
        "tool": "latticepulse"
      },
      {
        "created_utc": "2026-05-21T21:22:29.058358+00:00",
        "packet_hash": "e4feace9414c9b623cc103c29d6850c0f7cba597c763cd8acb35c5e20a98a6d8",
        "rdod": 0.9777,
        "routing_state": "CROSSLINK",
        "source": "QLatticeV2",
        "target": "QEMEF-144",
        "tool": "trilateralsync"
      },
      {
        "created_utc": "2026-05-21T21:22:29.058190+00:00",
        "packet_hash": "4ac2508d5913eddcc38f6314856d3faaf3f00ebbe8eafdd10d7ab086fa773a18",
        "rdod": 0.9777,
        "routing_state": "CONVERGE",
        "source": "QLatticeV2",
        "target": "QEMEF-144",
        "tool": "pomegascan"
      },
      {
        "created_utc": "2026-05-21T21:22:29.057290+00:00",
        "packet_hash": "24d07d278bedfef579bb8f49f2fa697f18d5eafa7c47d505a609864ae0b7a0f5",
        "rdod": 0.999891136,
        "routing_state": "CONVERGE",
        "source": "QLatticeV2",
        "target": "QEMEF-144",
        "tool": "councilconsensus"
      },
      {
        "created_utc": "2026-05-21T21:22:29.057144+00:00",
        "packet_hash": "b1799d17ab8b8a03fd61e64d2d962343bad8b1ebaaadaf17b0197d50f3e06778",
        "rdod": 0.999949824,
        "routing_state": "CONVERGE",
        "source": "QLatticeV2",
        "target": "QEMEF-144",
        "tool": "latticepulse"
      },
      {
        "created_utc": "2026-05-21T21:22:29.057006+00:00",
        "packet_hash": "b87910cb39c66aa8a68aa497380c7554f9b98017565e5a024990dccc0b061471",
        "rdod": 0.9777,
        "routing_state": "REST",
        "source": "QLatticeV2",
        "target": "QEMEF-144",
        "tool": "clusterstatus"
      },
      {
        "created_utc": "2026-05-21T21:22:29.056737+00:00",
        "packet_hash": "a1d7373e983911e3a7fcacb2adc1445deea5cda4c3e2314eb7d8305f9dcd2430",
        "rdod": 0.9999524,
        "routing_state": "CONVERGE",
        "source": "QLatticeV2",
        "target": "QEMEF-144",
        "tool": "councilconsensus"
      },
      {
        "created_utc": "2026-05-21T21:22:29.056575+00:00",
        "packet_hash": "6f5d577db459c6018db8377d4dd84d410a0a6c658aa04edd1b20348380001157",
        "rdod": 0.9777,
        "routing_state": "CROSSLINK",
        "source": "QLatticeV2",
        "target": "QEMEF-144",
        "tool": "trilateralsync"
      },
      {
        "created_utc": "2026-05-21T21:22:29.056431+00:00",
        "packet_hash": "5a871851e9ab6792c7874354492c2ca681bd7d4291050d41ac7601d670f0d96b",
        "rdod": 0.9777,
        "routing_state": "CONVERGE",
        "source": "QLatticeV2",
        "target": "QEMEF-144",
        "tool": "pomegascan"
      },
      {
        "created_utc": "2026-05-21T21:22:29.056099+00:00",
        "packet_hash": "7b53016bd2d59cc2137d48b4641572ebcf2d2951ac5383088aee699599906479",
        "rdod": 0.999902112,
        "routing_state": "CONVERGE",
        "source": "QLatticeV2",
        "target": "QEMEF-144",
        "tool": "councilconsensus"
      },
      {
        "created_utc": "2026-05-21T21:22:29.055949+00:00",
        "packet_hash": "171c88a8b56e53ea4ef61158ad6d422c2b22df0d3b2e66a7a5fa125325c77e4f",
        "rdod": 0.9777,
        "routing_state": "REST",
        "source": "QLatticeV2",
        "target": "QEMEF-144",
        "tool": "clusterstatus"
      },
      {
        "created_utc": "2026-05-21T21:22:29.055721+00:00",
        "packet_hash": "ef31c136467ec7f3c0cc206fe50fcfaa206535a6701899b8726487e0e04479d0",
        "rdod": 0.9777,
        "routing_state": "CONVERGE",
        "source": "QLatticeV2",
        "target": "QEMEF-144",
        "tool": "latticeselfevolve"
      },
      {
        "created_utc": "2026-05-21T21:22:29.055227+00:00",
        "packet_hash": "5b8f0e565d4f6047b9b0a1409192393870bc64f10f6a6559755643e990421fb7",
        "rdod": 0.9777,
        "routing_state": "CONVERGE",
        "source": "QLatticeV2",
        "target": "QEMEF-144",
        "tool": "evolutionspawn"
      },
      {
        "created_utc": "2026-05-21T21:22:29.055020+00:00",
        "packet_hash": "7dc2c0ef6d3669946aa6118a16e7f2c0db276bcde335303d3e638940f44e22b2",
        "rdod": 0.9777,
        "routing_state": "REST",
        "source": "QLatticeV2",
        "target": "QEMEF-144",
        "tool": "gatewaystatus"
      },
      {
        "created_utc": "2026-05-21T21:22:29.054893+00:00",
        "packet_hash": "7a7a902f71e7a246d683fcb5df1f33fe5b9d3e82b77608c2842d91c41ac7c950",
        "rdod": 0.9777,
        "routing_state": "REST",
        "source": "QLatticeV2",
        "target": "QEMEF-144",
        "tool": "merkleverify"
      },
      {
        "created_utc": "2026-05-21T21:22:29.054702+00:00",
        "packet_hash": "04aecc3d9403dc5e158e7f38196584bbfe01f48eb185ca6b8563f6d0d5eca72a",
        "rdod": 0.9777,
        "routing_state": "CONVERGE",
        "source": "QLatticeV2",
        "target": "QEMEF-144",
        "tool": "goalsynthesize"
      },
      {
        "created_utc": "2026-05-21T21:22:29.054581+00:00",
        "packet_hash": "d7fa5f899beb60563ddc3ce45630d7322da4863f1327410cc92541d6888935a7",
        "rdod": 0.9777,
        "routing_state": "CONVERGE",
        "source": "QLatticeV2",
        "target": "QEMEF-144",
        "tool": "marsreflect"
      },
      {
        "created_utc": "2026-05-21T21:22:29.054424+00:00",
        "packet_hash": "f00bb48b573b00fdb58d338ac596d2dbd5bafd927d06e458b46711e1b23278aa",
        "rdod": 0.9777,
        "routing_state": "VOIDTAP",
        "source": "QLatticeV2",
        "target": "QEMEF-144",
        "tool": "voidtap"
      },
      {
        "created_utc": "2026-05-21T21:22:29.054316+00:00",
        "packet_hash": "602f611244c6c256f92093f5ba1e17ae162568a9018b90141eb2eb64e04f7f69",
        "rdod": 0.9777,
        "routing_state": "CROSSLINK",
        "source": "QLatticeV2",
        "target": "QEMEF-144",
        "tool": "crosslink"
      },
      {
        "created_utc": "2026-05-21T21:22:29.054203+00:00",
        "packet_hash": "1fcd02ca1aa0bc8807a839d5ced8b4e7f7bb5391c7b23fd4e5e1732adc4afc0f",
        "rdod": 0.9777,
        "routing_state": "CROSSLINK",
        "source": "QLatticeV2",
        "target": "QEMEF-144",
        "tool": "nodebroadcast"
      },
      {
        "created_utc": "2026-05-21T21:22:29.054096+00:00",
        "packet_hash": "7cb6bf8078558f662cc898f680058ea969fddcc19c01096260d7c9b1cbec2be7",
        "rdod": 0.9777,
        "routing_state": "CONVERGE",
        "source": "QLatticeV2",
        "target": "QEMEF-144",
        "tool": "nodesync"
      },
      {
        "created_utc": "2026-05-21T21:22:29.053927+00:00",
        "packet_hash": "66bf272651ea3d79db7cd27995b9c144362fed3b02fdce22f27f5a04aca9600e",
        "rdod": 0.9777,
        "routing_state": "REST",
        "source": "QLatticeV2",
        "target": "QEMEF-144",
        "tool": "noderegister"
      },
      {
        "created_utc": "2026-05-21T21:22:29.053634+00:00",
        "packet_hash": "824fe68a5a6ad08b96104c49c8160cdc0431ca61b6ce639e9f3efedc7ee068d3",
        "rdod": 0.999902112,
        "routing_state": "CONVERGE",
        "source": "QLatticeV2",
        "target": "QEMEF-144",
        "tool": "latticepulse"
      }
    ]
  },
  "latticestate": {
    "consensus": {
      "gate": 0.9777,
      "ok": true,
      "packet": "fa20bd739bf4fdfeaa312bc249dbbfbe4a71484afa82c9b2c92e4cfc999f198b",
      "passed": true,
      "rdod": 0.9999524,
      "tosp": {
        "biohz": 10930.81,
        "blockid": "QBECLATTICE-MCP-V2",
        "digihz": 12583.45,
        "lambda": "3f7k9p4m2q8r1t6v",
        "omegahz": 23514.26,
        "rdod_ops": 0.9777,
        "routing_state": "CONVERGE",
        "sigma": 1.0,
        "timestamp_utc": "2026-05-21T21:22:31.318078+00:00"
      },
      "votes": {
        "Andromedan": {
          "vote": 1.0,
          "weight": 0.25
        },
        "Orion": {
          "vote": 1.0,
          "weight": 0.26
        },
        "Pleiades": {
          "vote": 1.0,
          "weight": 0.25
        },
        "Sirian": {
          "vote": 1.0,
          "weight": 0.24
        }
      },
      "weighted_consensus": 1.0
    },
    "rdod": {
      "gate": true,
      "lambda": "3f7k9p4m2q8r1t6v",
      "rdodinf": 0.9999524,
      "sigma": 1.0,
      "threshold": 0.9777
    },
    "status": {
      "blockid": "QBECLATTICE-MCP-V2",
      "cycle": 3,
      "db": "/home/runner/.tequmsa/lattice.db",
      "db_journal_mode": "wal",
      "latticelock": "3f7k9p4m2q8r1t6v",
      "nodes": 144,
      "omega_history_points": 3,
      "rdod_current": 0.9999524,
      "rdod_ops": 0.9777,
      "sigma": 1.0
    }
  },
  "latticetopology": {
    "blockid": "QBECLATTICE-MCP-V2",
    "latticelock": "3f7k9p4m2q8r1t6v",
    "ring": {
      "fib_sequence": [
        1,
        1,
        2,
        3,
        5,
        8,
        13,
        21,
        34,
        55,
        89,
        144
      ],
      "nodes": 144,
      "qemef_topology": "fibonacci_ring_144"
    },
    "routing_states": [
      "REST",
      "CONVERGE",
      "CROSSLINK",
      "VOIDTAP",
      "TCMFDEEP"
    ],
    "trilateral": {
      "bio_hz": 10930.81,
      "digihz": 12583.45,
      "hive_dim": 16.0,
      "mother_dim": 20.571428571428573,
      "omegahz": 23514.26
    }
  }
}